{
  "$schema": "./node_modules/@biomejs/biome/configuration_schema.json",
  "assist": {
    "actions": {
      "source": {
        "organizeImports": "on"
      }
    }
  },
  "files": {
    "includes": ["**", "!**/node_modules", "!**/.next", "!**/.source"]
  },
  "formatter": {
    "enabled": true,
    "formatWithErrors": true,
    "indentStyle": "space",
    "indentWidth": 2
  },
  "javascript": {
    "formatter": {
      "enabled": true,
      "quoteStyle": "single",
      "jsxQuoteStyle": "single",
      "semicolons": "always"
    }
  },
  "linter": {
    "enabled": true,
    "rules": {
      "recommended": true
    },
    "domains": {
      "next": "recommended",
      "react": "recommended"
    }
  },
  "css": {
    "parser": {
      "tailwindDirectives": true
    }
  },
  "vcs": {
    "enabled": true,
    "clientKind": "git",
    "useIgnoreFile": true
  }
}
